[
  {
    "roll": "2109047",
    "passwordHash": "$2b$10$mbhu/p0RryETAW8wxY.FuuAUBLw.sq3FZqVqr.5eCy/1jfL6atxkO"
  },
  {
    "roll": "2109031",
    "passwordHash": "$2a$10$avcNBKht6VzajHftIVCl1.nPNg7/UcXg4EYIfjiRdyqaqImO9X4R2"
  },
  {
    "roll": "2109052",
    "passwordHash": "$2a$10$avcNBKht6VzajHftIVCl1.nPNg7/UcXg4EYIfjiRdyqaqImO9X4R2"
  },
  {
    "roll": "2109038",
    "passwordHash": "$2a$10$avcNBKht6VzajHftIVCl1.nPNg7/UcXg4EYIfjiRdyqaqImO9X4R2"
  },
  {
    "roll": "2109049",
    "passwordHash": "$2a$10$avcNBKht6VzajHftIVCl1.nPNg7/UcXg4EYIfjiRdyqaqImO9X4R2"
  },
  {
    "roll": "2109050",
    "passwordHash": "$2a$10$avcNBKht6VzajHftIVCl1.nPNg7/UcXg4EYIfjiRdyqaqImO9X4R2"
  },
  {
    "roll": "2109032",
    "passwordHash": "$2a$10$avcNBKht6VzajHftIVCl1.nPNg7/UcXg4EYIfjiRdyqaqImO9X4R2"
  },
  {
    "roll": "2109042",
    "passwordHash": "$2a$10$avcNBKht6VzajHftIVCl1.nPNg7/UcXg4EYIfjiRdyqaqImO9X4R2"
  },
  {
    "roll": "2109060",
    "passwordHash": "$2a$10$avcNBKht6VzajHftIVCl1.nPNg7/UcXg4EYIfjiRdyqaqImO9X4R2"
  },
  {
    "roll": "2109059",
    "passwordHash": "$2a$10$avcNBKht6VzajHftIVCl1.nPNg7/UcXg4EYIfjiRdyqaqImO9X4R2"
  },
  {
    "roll": "2109033",
    "passwordHash": "$2a$10$avcNBKht6VzajHftIVCl1.nPNg7/UcXg4EYIfjiRdyqaqImO9X4R2"
  },
  {
    "roll": "2209005",
    "passwordHash": "$2a$10$avcNBKht6VzajHftIVCl1.nPNg7/UcXg4EYIfjiRdyqaqImO9X4R2"
  },
  {
    "roll": "2209004",
    "passwordHash": "$2a$10$avcNBKht6VzajHftIVCl1.nPNg7/UcXg4EYIfjiRdyqaqImO9X4R2"
  },
  {
    "roll": "2209022",
    "passwordHash": "$2a$10$avcNBKht6VzajHftIVCl1.nPNg7/UcXg4EYIfjiRdyqaqImO9X4R2"
  },
  {
    "roll": "2209011",
    "passwordHash": "$2a$10$avcNBKht6VzajHftIVCl1.nPNg7/UcXg4EYIfjiRdyqaqImO9X4R2"
  },
  {
    "roll": "2209003",
    "passwordHash": "$2a$10$avcNBKht6VzajHftIVCl1.nPNg7/UcXg4EYIfjiRdyqaqImO9X4R2"
  },
  {
    "roll": "2209034",
    "passwordHash": "$2a$10$avcNBKht6VzajHftIVCl1.nPNg7/UcXg4EYIfjiRdyqaqImO9X4R2"
  },
  {
    "roll": "2209050",
    "passwordHash": "$2a$10$avcNBKht6VzajHftIVCl1.nPNg7/UcXg4EYIfjiRdyqaqImO9X4R2"
  },
  {
    "roll": "2209049",
    "passwordHash": "$2a$10$avcNBKht6VzajHftIVCl1.nPNg7/UcXg4EYIfjiRdyqaqImO9X4R2"
  },
  {
    "roll": "2209032",
    "passwordHash": "$2a$10$avcNBKht6VzajHftIVCl1.nPNg7/UcXg4EYIfjiRdyqaqImO9X4R2"
  },
  {
    "roll": "2209012",
    "passwordHash": "$2a$10$avcNBKht6VzajHftIVCl1.nPNg7/UcXg4EYIfjiRdyqaqImO9X4R2"
  }
]
